std_vision/__init__.py
std_vision/communication.py
std_vision/contour.py
std_vision/converter.py
std_vision/draw.py
std_vision/geometry.py
std_vision/histogram.py
std_vision/mathematics.py
std_vision/morphology.py
std_vision/ros_tools.py
std_vision/threshold.py
std_vision/video.py
std_vision-1.0.4.dist-info/LICENSE
std_vision-1.0.4.dist-info/METADATA
std_vision-1.0.4.dist-info/WHEEL
std_vision-1.0.4.dist-info/top_level.txt
std_vision-1.0.4.dist-info/RECORD
